.clang-format
.flake8
.gitignore
.gitmodules
CHANGELOG.md
CODEOWNERS
CODE_OF_CONDUCT
Dockerfile
Dockerfile-cuda
Dockerfile-embedded
LICENSE
MANIFEST.in
Makefile
README.md
__init__.py
description.txt
packages.txt
setup.py
./src/opendr/__init__.py
./src/opendr/_setup.py
./src/opendr/_version.py
./src/opendr/control/__init__.py
./src/opendr/engine/__init__.py
./src/opendr/engine/constants.py
./src/opendr/engine/data.py
./src/opendr/engine/datasets.py
./src/opendr/engine/example_learner.py
./src/opendr/engine/learners.py
./src/opendr/engine/target.py
./src/opendr/perception/__init__.py
./src/opendr/perception/skeleton_based_action_recognition/README.md
./src/opendr/perception/skeleton_based_action_recognition/__init__.py
./src/opendr/perception/skeleton_based_action_recognition/continual_stgcn_learner.py
./src/opendr/perception/skeleton_based_action_recognition/dependencies.ini
./src/opendr/perception/skeleton_based_action_recognition/progressive_spatio_temporal_gcn_learner.py
./src/opendr/perception/skeleton_based_action_recognition/spatio_temporal_gcn_learner.py
./src/opendr/perception/skeleton_based_action_recognition/algorithm/__init__.py
./src/opendr/perception/skeleton_based_action_recognition/algorithm/datasets/__init__.py
./src/opendr/perception/skeleton_based_action_recognition/algorithm/datasets/feeder.py
./src/opendr/perception/skeleton_based_action_recognition/algorithm/datasets/kinetics400_classes.csv
./src/opendr/perception/skeleton_based_action_recognition/algorithm/datasets/kinetics_feeder.py
./src/opendr/perception/skeleton_based_action_recognition/algorithm/datasets/kinetics_gendata.py
./src/opendr/perception/skeleton_based_action_recognition/algorithm/datasets/ntu60_labels.csv
./src/opendr/perception/skeleton_based_action_recognition/algorithm/datasets/ntu_gendata.py
./src/opendr/perception/skeleton_based_action_recognition/algorithm/datasets/ntu_samples_with_missing_skeletons.txt
./src/opendr_toolkit_skeleton_based_action_recognition.egg-info/PKG-INFO
./src/opendr_toolkit_skeleton_based_action_recognition.egg-info/SOURCES.txt
./src/opendr_toolkit_skeleton_based_action_recognition.egg-info/dependency_links.txt
./src/opendr_toolkit_skeleton_based_action_recognition.egg-info/requires.txt
./src/opendr_toolkit_skeleton_based_action_recognition.egg-info/top_level.txt
